.gitignore
CHANGES.rst
README.rst
setup.py
src/pwt/__init__.py
src/pwt.recipe.closurebuilder.egg-info/PKG-INFO
src/pwt.recipe.closurebuilder.egg-info/SOURCES.txt
src/pwt.recipe.closurebuilder.egg-info/dependency_links.txt
src/pwt.recipe.closurebuilder.egg-info/entry_points.txt
src/pwt.recipe.closurebuilder.egg-info/namespace_packages.txt
src/pwt.recipe.closurebuilder.egg-info/not-zip-safe
src/pwt.recipe.closurebuilder.egg-info/requires.txt
src/pwt.recipe.closurebuilder.egg-info/top_level.txt
src/pwt/recipe/__init__.py
src/pwt/recipe/closurebuilder/README.txt
src/pwt/recipe/closurebuilder/__init__.py
src/pwt/recipe/closurebuilder/compiler-1111.jar
src/pwt/recipe/closurebuilder/tests.py
src/pwt/recipe/closurebuilder/build/closurebuilder.py
src/pwt/recipe/closurebuilder/build/depstree.py
src/pwt/recipe/closurebuilder/build/depstree_test.py
src/pwt/recipe/closurebuilder/build/depswriter.py
src/pwt/recipe/closurebuilder/build/jscompiler.py
src/pwt/recipe/closurebuilder/build/source.py
src/pwt/recipe/closurebuilder/build/source_test.py
src/pwt/recipe/closurebuilder/build/treescan.py
src/pwt/recipe/closurebuilder/goog/base.js