Metadata-Version: 1.0
Name: pwt.recipe.closurebuilder
Version: 0.9.8
Summary: zc.buildout recipe for closurebuilder
Home-page: https://github.com/mkerrin/pwt.recipe.closurebuilder
Author: Michael Kerrin
Author-email: michael.kerrin@gmail.com
License: UNKNOWN
Platform: UNKNOWN
